README.md
lexio/__init__.py
lexio/_version.py
lexio/types/__init__.py
pyproject.toml
lexio-0.1.3.dist-info/METADATA
lexio-0.1.3.dist-info/WHEEL
lexio-0.1.3.dist-info/RECORD
