Metadata-Version: 2.4
Name: lexio
Version: 0.1.3
Summary: Python type definitions for the lexio frontend library. Provides Pydantic models for type-safe interaction with the lexio UI components, including source references.
Project-URL: Homepage, https://github.com/renumics/lexio
Project-URL: Documentation, https://github.com/renumics/lexio/tree/main/python/lexio#readme
Project-URL: Repository, https://github.com/renumics/lexio.git
Project-URL: Bug Tracker, https://github.com/renumics/lexio/issues
Author: Renumics
Keywords: chatbot,frontend,lexio,pydantic,rag,rag-ui,types,typescript,ui
Classifier: Intended Audience :: Developers
Classifier: License :: OSI Approved :: GNU General Public License v3 (GPLv3)
Classifier: Programming Language :: Python :: 3
Classifier: Programming Language :: Python :: 3.9
Classifier: Programming Language :: Python :: 3.10
Classifier: Programming Language :: Python :: 3.11
Classifier: Programming Language :: Python :: 3.12
Classifier: Topic :: Software Development :: Libraries :: Python Modules
Classifier: Typing :: Typed
Requires-Python: >=3.9
Requires-Dist: pydantic>=2.0.0
Requires-Dist: typing-extensions>=4.0.0
Provides-Extra: dev
Requires-Dist: bump-my-version>=0.30.1; extra == 'dev'
Requires-Dist: datamodel-code-generator>=0.25.1; extra == 'dev'
Requires-Dist: hatch>=1.7.0; extra == 'dev'
Requires-Dist: pytest-asyncio>=0.21.0; extra == 'dev'
Requires-Dist: pytest-cov>=4.0.0; extra == 'dev'
Requires-Dist: pytest>=7.0.0; extra == 'dev'
Requires-Dist: twine>=4.0.0; extra == 'dev'
